pypifs/__init__.py
pypifs/_version.py
pypifs/opener.py
pypifs-0.0.2.dist-info/METADATA
pypifs-0.0.2.dist-info/WHEEL
pypifs-0.0.2.dist-info/entry_points.txt
pypifs-0.0.2.dist-info/top_level.txt
pypifs-0.0.2.dist-info/RECORD
