Metadata-Version: 2.1
Name: pypifs
Version: 0.0.2
Summary: Read files from python packages
Home-page: https://github.com/moremoban/pypifs
Author: C.W.
Author-email: wangc_2011@hotmail.com
License: MIT
Download-URL: https://github.com/moremoban/pypifs/archive/0.0.2.tar.gz
Keywords: python
Platform: UNKNOWN
Classifier: Topic :: Software Development :: Libraries
Classifier: Programming Language :: Python
Classifier: Intended Audience :: Developers
Classifier: Programming Language :: Python :: 2.6
Classifier: Programming Language :: Python :: 2.7
Classifier: Programming Language :: Python :: 3.3
Classifier: Programming Language :: Python :: 3.4
Classifier: Programming Language :: Python :: 3.5
Classifier: Programming Language :: Python :: 3.6
Classifier: Programming Language :: Python :: 3.7
Classifier: Programming Language :: Python :: 3.8
Requires-Dist: setuptools
Requires-Dist: fs (>=2.2.0)
Requires-Dist: importlib-metadata
